script_venv/__init__.py
script_venv/cli.py
script_venv/config.py
script_venv/factory.py
script_venv/script_venv.py
script_venv/venv.py
script_venv-0.7.1.dist-info/AUTHORS.rst
script_venv-0.7.1.dist-info/LICENSE
script_venv-0.7.1.dist-info/METADATA
script_venv-0.7.1.dist-info/WHEEL
script_venv-0.7.1.dist-info/entry_points.txt
script_venv-0.7.1.dist-info/top_level.txt
script_venv-0.7.1.dist-info/RECORD
