Metadata-Version: 2.1
Name: script-venv
Version: 0.7.1
Summary: A python package for script (and command) virtualisation with less typing.
Home-page: https://github.com/neongraal/script_venv
Author: Struan Lyall Judd
Author-email: sv@scifi.geek.nz
License: BSD license
Keywords: script_venv
Classifier: Development Status :: 4 - Beta
Classifier: Intended Audience :: Developers
Classifier: Intended Audience :: System Administrators
Classifier: License :: OSI Approved :: BSD License
Classifier: Natural Language :: English
Classifier: Programming Language :: Python :: 3
Classifier: Programming Language :: Python :: 3.10
Classifier: Programming Language :: Python :: 3.11
License-File: LICENSE
License-File: AUTHORS.rst
Requires-Dist: Click (>=6.0)
Requires-Dist: pathlib2
